ReadROOT/ErrorPropagation.py
ReadROOT/IOClasses.py
ReadROOT/QtClasses.py
ReadROOT/ValidInputs.py
ReadROOT/XML_Parser.py
ReadROOT/__init__.py
ReadROOT/config.json
ReadROOT/discord.mp3
ReadROOT/funcs.cpp
ReadROOT/funcs.hpp
ReadROOT/read_root.py
ReadROOT/read_root_gui.py
ReadROOT/read_root_gui_v2.py
ReadROOT/reload.py
ReadROOT/root_plotter.py
ReadROOT/wrap.cpp
ReadROOT/Images/Calculate.png
ReadROOT/Images/Clear.png
ReadROOT/Images/CompClear.png
ReadROOT/Images/Disabled0.png
ReadROOT/Images/Disabled1.png
ReadROOT/Images/Disabled2.png
ReadROOT/Images/Disabled3.png
ReadROOT/Images/DisabledSelect.png
ReadROOT/Images/DisabledSelectROI.png
ReadROOT/Images/EnergyHist.png
ReadROOT/Images/EnergyvsEnergyHist.png
ReadROOT/Images/MCS Graph.png
ReadROOT/Images/Off0.png
ReadROOT/Images/Off1.png
ReadROOT/Images/Off2.png
ReadROOT/Images/Off3.png
ReadROOT/Images/OffSelect.png
ReadROOT/Images/OffSelectROI.png
ReadROOT/Images/On0.png
ReadROOT/Images/On1.png
ReadROOT/Images/On2.png
ReadROOT/Images/On3.png
ReadROOT/Images/OnSelect.png
ReadROOT/Images/OnSelectROI.png
ReadROOT/Images/OpenFolder.png
ReadROOT/Images/OpenFolderCompass.png
ReadROOT/Images/PSDHist.png
ReadROOT/Images/PSDvsEnergyHist.png
ReadROOT/Images/Plot.png
ReadROOT/Images/PlotCompass.png
ReadROOT/Images/SaveCompass.png
ReadROOT/Images/SaveImage.png
ReadROOT/Images/TOFHist.png
ReadROOT/Images/TOFvsEnergyHist.png
ReadROOT/Images/TimeHist.png
ReadROOT/Images/axis.png
ReadROOT/Images/collapsed.png
ReadROOT/Images/delete.png
ReadROOT/Images/expanded.png
ReadROOT/Images/file_config.png
ReadROOT/Images/grid.png
ReadROOT/Images/histogram.png
ReadROOT/Images/info.png
ReadROOT/Images/line.png
ReadROOT/Images/save.png
ReadROOT/Images/settings.png
ReadROOT/Images/start.png
ReadROOT/Images/stop.png
ReadROOT/Images/time.png
ReadROOT/Images/CoMPASS/Coincidence.png
ReadROOT/Images/CoMPASS/Discriminator.png
ReadROOT/Images/CoMPASS/EnergyCalibration.png
ReadROOT/Images/CoMPASS/Input.png
ReadROOT/Images/CoMPASS/Misc.png
ReadROOT-2.5.12.dist-info/METADATA
ReadROOT-2.5.12.dist-info/WHEEL
ReadROOT-2.5.12.dist-info/top_level.txt
ReadROOT-2.5.12.dist-info/RECORD
