Metadata-Version: 2.1
Name: ReadROOT
Version: 2.5.12
Summary: Easy GUI made to read ROOT files created by the CoMPASS software distribued by CAEN.
Author: Chloé Legué
Author-email: chloe.legue@mail.mcgill.ca
Project-URL: Repository, https://github.com/Chujo58/ReadROOT
Project-URL: Documentation, https://github.com/Chujo58/ReadROOT/wiki
Requires-Python: >=3.10
Requires-Dist: uproot
Requires-Dist: bytechomp
Requires-Dist: numpy
Requires-Dist: spinmob
Requires-Dist: pandas
Requires-Dist: pyqtgraph (==0.13.3)
Requires-Dist: darkdetect
Requires-Dist: pyqt5
Requires-Dist: scipy
Requires-Dist: matplotlib
Requires-Dist: superqt
Requires-Dist: bs4
Requires-Dist: tk
Requires-Dist: pint
Requires-Dist: colorama
Requires-Dist: termcolor
Requires-Dist: cppimport
Requires-Dist: mpl-scatter-density
Requires-Dist: rich
Requires-Dist: pyautogui
Requires-Dist: playsound (==1.2.2)
